{"101050601": {"yearAvgTemp": ["-22", "-18", "-8", "5", "14", "19", "22", "20", "12", "2", "-10", "-20"], "yearMaxTemp": ["-16", "-11", "-1", "11", "20", "25", "27", "26", "19", "9", "-5", "-15"], "yearMinTemp": ["-27", "-24", "-14", "-2", "7", "14", "17", "15", "7", "-3", "-15", "-24"], "yearAvgHumidity": ["65", "62", "58", "48", "54", "70", "78", "79", "72", "63", "69", "70"], "yearAvgRain": ["4", "8", "6", "14", "55", "101", "150", "92", "74", "27", "12", "10"], "yearAvgRainDay": ["7", "5", "4", "6", "10", "14", "15", "14", "11", "7", "7", "8"], "yearAvgAqi": ["43", "37", "48", "46", "39", "33", "31", "36", "33", "33", "50", "49"], "yearAqi": [{"aqiLv0": ["551", "74.26"], "aqiLv1": ["160", "21.56"], "aqiLv2": ["29", "3.91"], "aqiLv3": ["2", "0.27"], "aqiLv4": ["0", "0.0"], "aqiLv5": ["0", "0.0"]}, {"aqiLv0": ["525", "80.03"], "aqiLv1": ["127", "19.36"], "aqiLv2": ["3", "0.46"], "aqiLv3": ["0", "0.0"], "aqiLv4": ["1", "0.15"], "aqiLv5": ["0", "0.0"]}, {"aqiLv0": ["576", "77.73"], "aqiLv1": ["131", "17.68"], "aqiLv2": ["12", "1.62"], "aqiLv3": ["7", "0.94"], "aqiLv4": ["11", "1.48"], "aqiLv5": ["4", "0.54"]}, {"aqiLv0": ["493", "78.13"], "aqiLv1": ["109", "17.27"], "aqiLv2": ["11", "1.74"], "aqiLv3": ["11", "1.74"], "aqiLv4": ["5", "0.79"], "aqiLv5": ["2", "0.32"]}, {"aqiLv0": ["558", "83.53"], "aqiLv1": ["102", "15.27"], "aqiLv2": ["8", "1.2"], "aqiLv3": ["0", "0.0"], "aqiLv4": ["0", "0.0"], "aqiLv5": ["0", "0.0"]}, {"aqiLv0": ["576", "92.46"], "aqiLv1": ["43", "6.9"], "aqiLv2": ["4", "0.64"], "aqiLv3": ["0", "0.0"], "aqiLv4": ["0", "0.0"], "aqiLv5": ["0", "0.0"]}, {"aqiLv0": ["701", "97.5"], "aqiLv1": ["18", "2.5"], "aqiLv2": ["0", "0.0"], "aqiLv3": ["0", "0.0"], "aqiLv4": ["0", "0.0"], "aqiLv5": ["0", "0.0"]}, {"aqiLv0": ["676", "91.11"], "aqiLv1": ["66", "8.89"], "aqiLv2": ["0", "0.0"], "aqiLv3": ["0", "0.0"], "aqiLv4": ["0", "0.0"], "aqiLv5": ["0", "0.0"]}, {"aqiLv0": ["622", "90.01"], "aqiLv1": ["69", "9.99"], "aqiLv2": ["0", "0.0"], "aqiLv3": ["0", "0.0"], "aqiLv4": ["0", "0.0"], "aqiLv5": ["0", "0.0"]}, {"aqiLv0": ["592", "82.45"], "aqiLv1": ["126", "17.55"], "aqiLv2": ["0", "0.0"], "aqiLv3": ["0", "0.0"], "aqiLv4": ["0", "0.0"], "aqiLv5": ["0", "0.0"]}, {"aqiLv0": ["390", "57.44"], "aqiLv1": ["286", "42.12"], "aqiLv2": ["3", "0.44"], "aqiLv3": ["0", "0.0"], "aqiLv4": ["0", "0.0"], "aqiLv5": ["0", "0.0"]}, {"aqiLv0": ["442", "62.87"], "aqiLv1": ["250", "35.56"], "aqiLv2": ["11", "1.56"], "aqiLv3": ["0", "0.0"], "aqiLv4": ["0", "0.0"], "aqiLv5": ["0", "0.0"]}], "SeasonAvgTmax": [10.0, 26.0, 7.0, -14.0], "SeasonAvgTmin": [-3.0, 15.0, -3.0, -25.0], "SeasonAvgRain": [75.0, 343.0, 113.0, 22.0], "AqiFlag": "true"}}