{"101090501": {"yearAvgTemp": ["-6", "-2", "6", "14", "21", "24", "26", "25", "20", "13", "3", "-4"], "yearMaxTemp": ["1", "5", "12", "20", "27", "30", "31", "30", "26", "19", "10", "3"], "yearMinTemp": ["-12", "-8", "-1", "7", "14", "19", "22", "21", "15", "7", "-2", "-9"], "yearAvgHumidity": ["59", "58", "50", "50", "52", "65", "76", "78", "74", "69", "66", "60"], "yearAvgRain": ["3", "8", "6", "29", "26", "93", "166", "141", "61", "30", "16", "3"], "yearAvgRainDay": ["2", "3", "2", "6", "6", "10", "11", "10", "6", "4", "4", "2"], "yearAvgAqi": ["85", "101", "137", "103", "103", "105", "78", "73", "67", "83", "124", "100"], "yearAqi": [{"aqiLv0": ["115", "15.62"], "aqiLv1": ["430", "58.42"], "aqiLv2": ["116", "15.76"], "aqiLv3": ["65", "8.83"], "aqiLv4": ["10", "1.36"], "aqiLv5": ["0", "0.0"]}, {"aqiLv0": ["96", "14.75"], "aqiLv1": ["294", "45.16"], "aqiLv2": ["132", "20.28"], "aqiLv3": ["73", "11.21"], "aqiLv4": ["55", "8.45"], "aqiLv5": ["1", "0.15"]}, {"aqiLv0": ["33", "4.44"], "aqiLv1": ["313", "42.07"], "aqiLv2": ["162", "21.77"], "aqiLv3": ["104", "13.98"], "aqiLv4": ["86", "11.56"], "aqiLv5": ["46", "6.18"]}, {"aqiLv0": ["115", "18.23"], "aqiLv1": ["262", "41.52"], "aqiLv2": ["165", "26.15"], "aqiLv3": ["42", "6.66"], "aqiLv4": ["42", "6.66"], "aqiLv5": ["5", "0.79"]}, {"aqiLv0": ["49", "7.36"], "aqiLv1": ["363", "54.5"], "aqiLv2": ["213", "31.98"], "aqiLv3": ["19", "2.85"], "aqiLv4": ["12", "1.8"], "aqiLv5": ["10", "1.5"]}, {"aqiLv0": ["53", "8.51"], "aqiLv1": ["375", "60.19"], "aqiLv2": ["163", "26.16"], "aqiLv3": ["25", "4.01"], "aqiLv4": ["7", "1.12"], "aqiLv5": ["0", "0.0"]}, {"aqiLv0": ["139", "19.36"], "aqiLv1": ["486", "67.69"], "aqiLv2": ["90", "12.53"], "aqiLv3": ["3", "0.42"], "aqiLv4": ["0", "0.0"], "aqiLv5": ["0", "0.0"]}, {"aqiLv0": ["213", "28.9"], "aqiLv1": ["446", "60.52"], "aqiLv2": ["76", "10.31"], "aqiLv3": ["2", "0.27"], "aqiLv4": ["0", "0.0"], "aqiLv5": ["0", "0.0"]}, {"aqiLv0": ["250", "36.13"], "aqiLv1": ["362", "52.31"], "aqiLv2": ["79", "11.42"], "aqiLv3": ["1", "0.14"], "aqiLv4": ["0", "0.0"], "aqiLv5": ["0", "0.0"]}, {"aqiLv0": ["190", "26.35"], "aqiLv1": ["349", "48.4"], "aqiLv2": ["133", "18.45"], "aqiLv3": ["30", "4.16"], "aqiLv4": ["19", "2.64"], "aqiLv5": ["0", "0.0"]}, {"aqiLv0": ["55", "8.22"], "aqiLv1": ["250", "37.37"], "aqiLv2": ["198", "29.6"], "aqiLv3": ["65", "9.72"], "aqiLv4": ["66", "9.87"], "aqiLv5": ["35", "5.23"]}, {"aqiLv0": ["80", "11.41"], "aqiLv1": ["394", "56.21"], "aqiLv2": ["136", "19.4"], "aqiLv3": ["50", "7.13"], "aqiLv4": ["38", "5.42"], "aqiLv5": ["3", "0.43"]}], "SeasonAvgTmax": [19.0, 30.0, 18.0, 3.0], "SeasonAvgTmin": [6.0, 20.0, 6.0, -9.0], "SeasonAvgRain": [61.0, 400.0, 107.0, 14.0], "AqiFlag": "true"}}