{"101250607": {"yearAvgTemp": ["5", "7", "12", "17", "22", "25", "28", "28", "23", "18", "12", "7"], "yearAvgRainDay": ["8", "10", "12", "13", "15", "13", "9", "9", "11", "11", "12", "8"], "AqiFlag": "false", "yearAqi": [{"aqiLv1": ["-1", "-1"], "aqiLv0": ["-1", "-1"], "aqiLv3": ["-1", "-1"], "aqiLv2": ["-1", "-1"], "aqiLv5": ["-1", "-1"], "aqiLv4": ["-1", "-1"]}, {"aqiLv1": ["-1", "-1"], "aqiLv0": ["-1", "-1"], "aqiLv3": ["-1", "-1"], "aqiLv2": ["-1", "-1"], "aqiLv5": ["-1", "-1"], "aqiLv4": ["-1", "-1"]}, {"aqiLv1": ["-1", "-1"], "aqiLv0": ["-1", "-1"], "aqiLv3": ["-1", "-1"], "aqiLv2": ["-1", "-1"], "aqiLv5": ["-1", "-1"], "aqiLv4": ["-1", "-1"]}, {"aqiLv1": ["-1", "-1"], "aqiLv0": ["-1", "-1"], "aqiLv3": ["-1", "-1"], "aqiLv2": ["-1", "-1"], "aqiLv5": ["-1", "-1"], "aqiLv4": ["-1", "-1"]}, {"aqiLv1": ["-1", "-1"], "aqiLv0": ["-1", "-1"], "aqiLv3": ["-1", "-1"], "aqiLv2": ["-1", "-1"], "aqiLv5": ["-1", "-1"], "aqiLv4": ["-1", "-1"]}, {"aqiLv1": ["-1", "-1"], "aqiLv0": ["-1", "-1"], "aqiLv3": ["-1", "-1"], "aqiLv2": ["-1", "-1"], "aqiLv5": ["-1", "-1"], "aqiLv4": ["-1", "-1"]}, {"aqiLv1": ["-1", "-1"], "aqiLv0": ["-1", "-1"], "aqiLv3": ["-1", "-1"], "aqiLv2": ["-1", "-1"], "aqiLv5": ["-1", "-1"], "aqiLv4": ["-1", "-1"]}, {"aqiLv1": ["-1", "-1"], "aqiLv0": ["-1", "-1"], "aqiLv3": ["-1", "-1"], "aqiLv2": ["-1", "-1"], "aqiLv5": ["-1", "-1"], "aqiLv4": ["-1", "-1"]}, {"aqiLv1": ["-1", "-1"], "aqiLv0": ["-1", "-1"], "aqiLv3": ["-1", "-1"], "aqiLv2": ["-1", "-1"], "aqiLv5": ["-1", "-1"], "aqiLv4": ["-1", "-1"]}, {"aqiLv1": ["-1", "-1"], "aqiLv0": ["-1", "-1"], "aqiLv3": ["-1", "-1"], "aqiLv2": ["-1", "-1"], "aqiLv5": ["-1", "-1"], "aqiLv4": ["-1", "-1"]}, {"aqiLv1": ["-1", "-1"], "aqiLv0": ["-1", "-1"], "aqiLv3": ["-1", "-1"], "aqiLv2": ["-1", "-1"], "aqiLv5": ["-1", "-1"], "aqiLv4": ["-1", "-1"]}, {"aqiLv1": ["-1", "-1"], "aqiLv0": ["-1", "-1"], "aqiLv3": ["-1", "-1"], "aqiLv2": ["-1", "-1"], "aqiLv5": ["-1", "-1"], "aqiLv4": ["-1", "-1"]}], "yearMinTemp": ["2", "4", "8", "13", "18", "21", "25", "24", "20", "15", "9", "4"], "yearAvgRain": ["34", "36", "91", "145", "187", "262", "201", "138", "131", "100", "75", "28"], "yearMaxTemp": ["9", "11", "17", "23", "26", "30", "33", "33", "28", "23", "16", "11"], "SeasonAvgTmin": [13.0, 23.0, 15.0, 3.0], "SeasonAvgRain": [425.0, 601.0, 307.0, 100.0], "SeasonAvgTmax": [22.0, 32.0, 22.0, 10.0], "yearAvgHumidity": ["72", "74", "73", "74", "77", "81", "77", "75", "78", "76", "80", "73"], "yearAvgAqi": ["-1", "-1", "-1", "-1", "-1", "-1", "-1", "-1", "-1", "-1", "-1", "-1"]}}