{"101201107": {"yearAvgTemp": ["3", "5", "11", "17", "21", "26", "28", "27", "22", "17", "11", "5"], "yearAvgRainDay": ["4", "7", "7", "8", "11", "9", "10", "9", "11", "10", "9", "4"], "AqiFlag": "false", "yearAqi": [{"aqiLv1": ["-1", "-1"], "aqiLv0": ["-1", "-1"], "aqiLv3": ["-1", "-1"], "aqiLv2": ["-1", "-1"], "aqiLv5": ["-1", "-1"], "aqiLv4": ["-1", "-1"]}, {"aqiLv1": ["-1", "-1"], "aqiLv0": ["-1", "-1"], "aqiLv3": ["-1", "-1"], "aqiLv2": ["-1", "-1"], "aqiLv5": ["-1", "-1"], "aqiLv4": ["-1", "-1"]}, {"aqiLv1": ["-1", "-1"], "aqiLv0": ["-1", "-1"], "aqiLv3": ["-1", "-1"], "aqiLv2": ["-1", "-1"], "aqiLv5": ["-1", "-1"], "aqiLv4": ["-1", "-1"]}, {"aqiLv1": ["-1", "-1"], "aqiLv0": ["-1", "-1"], "aqiLv3": ["-1", "-1"], "aqiLv2": ["-1", "-1"], "aqiLv5": ["-1", "-1"], "aqiLv4": ["-1", "-1"]}, {"aqiLv1": ["-1", "-1"], "aqiLv0": ["-1", "-1"], "aqiLv3": ["-1", "-1"], "aqiLv2": ["-1", "-1"], "aqiLv5": ["-1", "-1"], "aqiLv4": ["-1", "-1"]}, {"aqiLv1": ["-1", "-1"], "aqiLv0": ["-1", "-1"], "aqiLv3": ["-1", "-1"], "aqiLv2": ["-1", "-1"], "aqiLv5": ["-1", "-1"], "aqiLv4": ["-1", "-1"]}, {"aqiLv1": ["-1", "-1"], "aqiLv0": ["-1", "-1"], "aqiLv3": ["-1", "-1"], "aqiLv2": ["-1", "-1"], "aqiLv5": ["-1", "-1"], "aqiLv4": ["-1", "-1"]}, {"aqiLv1": ["-1", "-1"], "aqiLv0": ["-1", "-1"], "aqiLv3": ["-1", "-1"], "aqiLv2": ["-1", "-1"], "aqiLv5": ["-1", "-1"], "aqiLv4": ["-1", "-1"]}, {"aqiLv1": ["-1", "-1"], "aqiLv0": ["-1", "-1"], "aqiLv3": ["-1", "-1"], "aqiLv2": ["-1", "-1"], "aqiLv5": ["-1", "-1"], "aqiLv4": ["-1", "-1"]}, {"aqiLv1": ["-1", "-1"], "aqiLv0": ["-1", "-1"], "aqiLv3": ["-1", "-1"], "aqiLv2": ["-1", "-1"], "aqiLv5": ["-1", "-1"], "aqiLv4": ["-1", "-1"]}, {"aqiLv1": ["-1", "-1"], "aqiLv0": ["-1", "-1"], "aqiLv3": ["-1", "-1"], "aqiLv2": ["-1", "-1"], "aqiLv5": ["-1", "-1"], "aqiLv4": ["-1", "-1"]}, {"aqiLv1": ["-1", "-1"], "aqiLv0": ["-1", "-1"], "aqiLv3": ["-1", "-1"], "aqiLv2": ["-1", "-1"], "aqiLv5": ["-1", "-1"], "aqiLv4": ["-1", "-1"]}], "yearMinTemp": ["0", "2", "7", "12", "17", "22", "25", "24", "19", "14", "7", "2"], "yearAvgRain": ["13", "18", "35", "65", "101", "73", "90", "117", "110", "73", "51", "10"], "yearMaxTemp": ["8", "10", "16", "23", "27", "31", "33", "32", "27", "22", "15", "10"], "SeasonAvgTmin": [12.0, 23.0, 14.0, 1.0], "SeasonAvgRain": [202.0, 281.0, 234.0, 42.0], "SeasonAvgTmax": [22.0, 32.0, 21.0, 9.0], "yearAvgHumidity": ["66", "69", "67", "68", "70", "71", "76", "75", "77", "74", "76", "65"], "yearAvgAqi": ["-1", "-1", "-1", "-1", "-1", "-1", "-1", "-1", "-1", "-1", "-1", "-1"]}}