{"101250700": {"yearAvgTemp": ["6", "8", "12", "18", "23", "26", "30", "29", "24", "19", "13", "8"], "yearMaxTemp": ["9", "12", "17", "23", "27", "30", "34", "33", "28", "23", "17", "11"], "yearMinTemp": ["3", "5", "9", "15", "19", "23", "27", "26", "22", "16", "10", "5"], "yearAvgHumidity": ["72", "74", "75", "73", "74", "76", "68", "71", "75", "73", "76", "71"], "yearAvgRain": ["54", "71", "142", "181", "209", "213", "160", "113", "111", "77", "92", "66"], "yearAvgRainDay": ["12", "13", "16", "15", "16", "14", "10", "11", "11", "11", "13", "11"], "yearAvgAqi": ["83", "85", "55", "64", "49", "42", "40", "42", "44", "58", "62", "97"], "yearAqi": [{"aqiLv0": ["117", "15.92"], "aqiLv1": ["457", "62.18"], "aqiLv2": ["135", "18.37"], "aqiLv3": ["12", "1.63"], "aqiLv4": ["14", "1.9"], "aqiLv5": ["0", "0.0"]}, {"aqiLv0": ["120", "18.29"], "aqiLv1": ["346", "52.74"], "aqiLv2": ["148", "22.56"], "aqiLv3": ["32", "4.88"], "aqiLv4": ["10", "1.52"], "aqiLv5": ["0", "0.0"]}, {"aqiLv0": ["281", "38.13"], "aqiLv1": ["451", "61.19"], "aqiLv2": ["5", "0.68"], "aqiLv3": ["0", "0.0"], "aqiLv4": ["0", "0.0"], "aqiLv5": ["0", "0.0"]}, {"aqiLv0": ["206", "32.59"], "aqiLv1": ["350", "55.38"], "aqiLv2": ["50", "7.91"], "aqiLv3": ["22", "3.48"], "aqiLv4": ["4", "0.63"], "aqiLv5": ["0", "0.0"]}, {"aqiLv0": ["419", "62.72"], "aqiLv1": ["240", "35.93"], "aqiLv2": ["7", "1.05"], "aqiLv3": ["2", "0.3"], "aqiLv4": ["0", "0.0"], "aqiLv5": ["0", "0.0"]}, {"aqiLv0": ["481", "76.96"], "aqiLv1": ["129", "20.64"], "aqiLv2": ["15", "2.4"], "aqiLv3": ["0", "0.0"], "aqiLv4": ["0", "0.0"], "aqiLv5": ["0", "0.0"]}, {"aqiLv0": ["572", "79.55"], "aqiLv1": ["147", "20.45"], "aqiLv2": ["0", "0.0"], "aqiLv3": ["0", "0.0"], "aqiLv4": ["0", "0.0"], "aqiLv5": ["0", "0.0"]}, {"aqiLv0": ["570", "76.82"], "aqiLv1": ["172", "23.18"], "aqiLv2": ["0", "0.0"], "aqiLv3": ["0", "0.0"], "aqiLv4": ["0", "0.0"], "aqiLv5": ["0", "0.0"]}, {"aqiLv0": ["447", "65.07"], "aqiLv1": ["240", "34.93"], "aqiLv2": ["0", "0.0"], "aqiLv3": ["0", "0.0"], "aqiLv4": ["0", "0.0"], "aqiLv5": ["0", "0.0"]}, {"aqiLv0": ["187", "26.04"], "aqiLv1": ["524", "72.98"], "aqiLv2": ["7", "0.97"], "aqiLv3": ["0", "0.0"], "aqiLv4": ["0", "0.0"], "aqiLv5": ["0", "0.0"]}, {"aqiLv0": ["232", "34.27"], "aqiLv1": ["390", "57.61"], "aqiLv2": ["40", "5.91"], "aqiLv3": ["11", "1.62"], "aqiLv4": ["4", "0.59"], "aqiLv5": ["0", "0.0"]}, {"aqiLv0": ["99", "14.1"], "aqiLv1": ["357", "50.85"], "aqiLv2": ["134", "19.09"], "aqiLv3": ["59", "8.4"], "aqiLv4": ["53", "7.55"], "aqiLv5": ["0", "0.0"]}], "SeasonAvgTmax": [22.0, 32.0, 22.0, 10.0], "SeasonAvgTmin": [14.0, 25.0, 16.0, 4.0], "SeasonAvgRain": [532.0, 486.0, 280.0, 191.0], "AqiFlag": "true"}}