{"101290113": {"yearAvgTemp": ["6", "9", "12", "14", "16", "17", "17", "16", "15", "13", "10", "6"], "yearAvgRainDay": ["4", "2", "5", "8", "10", "16", "19", "21", "14", "13", "5", "4"], "AqiFlag": "false", "yearAqi": [{"aqiLv1": ["-1", "-1"], "aqiLv0": ["-1", "-1"], "aqiLv3": ["-1", "-1"], "aqiLv2": ["-1", "-1"], "aqiLv5": ["-1", "-1"], "aqiLv4": ["-1", "-1"]}, {"aqiLv1": ["-1", "-1"], "aqiLv0": ["-1", "-1"], "aqiLv3": ["-1", "-1"], "aqiLv2": ["-1", "-1"], "aqiLv5": ["-1", "-1"], "aqiLv4": ["-1", "-1"]}, {"aqiLv1": ["-1", "-1"], "aqiLv0": ["-1", "-1"], "aqiLv3": ["-1", "-1"], "aqiLv2": ["-1", "-1"], "aqiLv5": ["-1", "-1"], "aqiLv4": ["-1", "-1"]}, {"aqiLv1": ["-1", "-1"], "aqiLv0": ["-1", "-1"], "aqiLv3": ["-1", "-1"], "aqiLv2": ["-1", "-1"], "aqiLv5": ["-1", "-1"], "aqiLv4": ["-1", "-1"]}, {"aqiLv1": ["-1", "-1"], "aqiLv0": ["-1", "-1"], "aqiLv3": ["-1", "-1"], "aqiLv2": ["-1", "-1"], "aqiLv5": ["-1", "-1"], "aqiLv4": ["-1", "-1"]}, {"aqiLv1": ["-1", "-1"], "aqiLv0": ["-1", "-1"], "aqiLv3": ["-1", "-1"], "aqiLv2": ["-1", "-1"], "aqiLv5": ["-1", "-1"], "aqiLv4": ["-1", "-1"]}, {"aqiLv1": ["-1", "-1"], "aqiLv0": ["-1", "-1"], "aqiLv3": ["-1", "-1"], "aqiLv2": ["-1", "-1"], "aqiLv5": ["-1", "-1"], "aqiLv4": ["-1", "-1"]}, {"aqiLv1": ["-1", "-1"], "aqiLv0": ["-1", "-1"], "aqiLv3": ["-1", "-1"], "aqiLv2": ["-1", "-1"], "aqiLv5": ["-1", "-1"], "aqiLv4": ["-1", "-1"]}, {"aqiLv1": ["-1", "-1"], "aqiLv0": ["-1", "-1"], "aqiLv3": ["-1", "-1"], "aqiLv2": ["-1", "-1"], "aqiLv5": ["-1", "-1"], "aqiLv4": ["-1", "-1"]}, {"aqiLv1": ["-1", "-1"], "aqiLv0": ["-1", "-1"], "aqiLv3": ["-1", "-1"], "aqiLv2": ["-1", "-1"], "aqiLv5": ["-1", "-1"], "aqiLv4": ["-1", "-1"]}, {"aqiLv1": ["-1", "-1"], "aqiLv0": ["-1", "-1"], "aqiLv3": ["-1", "-1"], "aqiLv2": ["-1", "-1"], "aqiLv5": ["-1", "-1"], "aqiLv4": ["-1", "-1"]}, {"aqiLv1": ["-1", "-1"], "aqiLv0": ["-1", "-1"], "aqiLv3": ["-1", "-1"], "aqiLv2": ["-1", "-1"], "aqiLv5": ["-1", "-1"], "aqiLv4": ["-1", "-1"]}], "yearMinTemp": ["2", "5", "7", "10", "12", "14", "14", "14", "13", "10", "6", "3"], "yearAvgRain": ["18", "5", "22", "32", "67", "175", "186", "196", "156", "94", "28", "18"], "yearMaxTemp": ["13", "16", "19", "21", "23", "23", "22", "22", "20", "18", "16", "13"], "SeasonAvgTmin": [10.0, 14.0, 10.0, 3.0], "SeasonAvgRain": [123.0, 558.0, 279.0, 42.0], "SeasonAvgTmax": [21.0, 22.0, 18.0, 14.0], "yearAvgHumidity": ["72", "55", "55", "62", "70", "85", "89", "89", "89", "87", "79", "79"], "yearAvgAqi": ["-1", "-1", "-1", "-1", "-1", "-1", "-1", "-1", "-1", "-1", "-1", "-1"]}}