{"101240906": {"yearAvgTemp": ["6", "8", "12", "18", "23", "26", "29", "28", "25", "20", "13", "8"], "yearAvgRainDay": ["15", "14", "18", "18", "17", "16", "12", "12", "9", "9", "14", "13"], "AqiFlag": "false", "yearAqi": [{"aqiLv1": ["-1", "-1"], "aqiLv0": ["-1", "-1"], "aqiLv3": ["-1", "-1"], "aqiLv2": ["-1", "-1"], "aqiLv5": ["-1", "-1"], "aqiLv4": ["-1", "-1"]}, {"aqiLv1": ["-1", "-1"], "aqiLv0": ["-1", "-1"], "aqiLv3": ["-1", "-1"], "aqiLv2": ["-1", "-1"], "aqiLv5": ["-1", "-1"], "aqiLv4": ["-1", "-1"]}, {"aqiLv1": ["-1", "-1"], "aqiLv0": ["-1", "-1"], "aqiLv3": ["-1", "-1"], "aqiLv2": ["-1", "-1"], "aqiLv5": ["-1", "-1"], "aqiLv4": ["-1", "-1"]}, {"aqiLv1": ["-1", "-1"], "aqiLv0": ["-1", "-1"], "aqiLv3": ["-1", "-1"], "aqiLv2": ["-1", "-1"], "aqiLv5": ["-1", "-1"], "aqiLv4": ["-1", "-1"]}, {"aqiLv1": ["-1", "-1"], "aqiLv0": ["-1", "-1"], "aqiLv3": ["-1", "-1"], "aqiLv2": ["-1", "-1"], "aqiLv5": ["-1", "-1"], "aqiLv4": ["-1", "-1"]}, {"aqiLv1": ["-1", "-1"], "aqiLv0": ["-1", "-1"], "aqiLv3": ["-1", "-1"], "aqiLv2": ["-1", "-1"], "aqiLv5": ["-1", "-1"], "aqiLv4": ["-1", "-1"]}, {"aqiLv1": ["-1", "-1"], "aqiLv0": ["-1", "-1"], "aqiLv3": ["-1", "-1"], "aqiLv2": ["-1", "-1"], "aqiLv5": ["-1", "-1"], "aqiLv4": ["-1", "-1"]}, {"aqiLv1": ["-1", "-1"], "aqiLv0": ["-1", "-1"], "aqiLv3": ["-1", "-1"], "aqiLv2": ["-1", "-1"], "aqiLv5": ["-1", "-1"], "aqiLv4": ["-1", "-1"]}, {"aqiLv1": ["-1", "-1"], "aqiLv0": ["-1", "-1"], "aqiLv3": ["-1", "-1"], "aqiLv2": ["-1", "-1"], "aqiLv5": ["-1", "-1"], "aqiLv4": ["-1", "-1"]}, {"aqiLv1": ["-1", "-1"], "aqiLv0": ["-1", "-1"], "aqiLv3": ["-1", "-1"], "aqiLv2": ["-1", "-1"], "aqiLv5": ["-1", "-1"], "aqiLv4": ["-1", "-1"]}, {"aqiLv1": ["-1", "-1"], "aqiLv0": ["-1", "-1"], "aqiLv3": ["-1", "-1"], "aqiLv2": ["-1", "-1"], "aqiLv5": ["-1", "-1"], "aqiLv4": ["-1", "-1"]}, {"aqiLv1": ["-1", "-1"], "aqiLv0": ["-1", "-1"], "aqiLv3": ["-1", "-1"], "aqiLv2": ["-1", "-1"], "aqiLv5": ["-1", "-1"], "aqiLv4": ["-1", "-1"]}], "yearMinTemp": ["4", "6", "9", "15", "19", "23", "25", "25", "22", "16", "10", "5"], "yearAvgRain": ["71", "78", "197", "184", "192", "258", "195", "114", "81", "50", "145", "94"], "yearMaxTemp": ["10", "12", "17", "23", "27", "31", "34", "34", "30", "25", "18", "12"], "SeasonAvgTmin": [14.0, 24.0, 16.0, 5.0], "SeasonAvgRain": [573.0, 568.0, 277.0, 245.0], "SeasonAvgTmax": [22.0, 33.0, 24.0, 11.0], "yearAvgHumidity": ["79", "80", "81", "78", "80", "80", "73", "75", "77", "74", "80", "76"], "yearAvgAqi": ["-1", "-1", "-1", "-1", "-1", "-1", "-1", "-1", "-1", "-1", "-1", "-1"]}}