{"101230101": {"yearAvgTemp": ["11", "12", "14", "19", "23", "27", "30", "29", "27", "23", "18", "13"], "yearMaxTemp": ["15", "17", "20", "24", "28", "31", "35", "34", "31", "27", "22", "17"], "yearMinTemp": ["9", "9", "11", "16", "20", "24", "26", "26", "24", "20", "16", "11"], "yearAvgHumidity": ["72", "74", "73", "71", "78", "80", "72", "74", "72", "66", "74", "69"], "yearAvgRain": ["66", "71", "109", "161", "189", "248", "152", "259", "150", "40", "86", "52"], "yearAvgRainDay": ["10", "12", "14", "15", "18", "16", "10", "14", "11", "7", "11", "10"], "yearAvgAqi": ["46", "55", "53", "71", "62", "51", "43", "45", "42", "53", "37", "40"], "yearAqi": [{"aqiLv0": ["426", "57.96"], "aqiLv1": ["296", "40.27"], "aqiLv2": ["13", "1.77"], "aqiLv3": ["0", "0.0"], "aqiLv4": ["0", "0.0"], "aqiLv5": ["0", "0.0"]}, {"aqiLv0": ["299", "45.58"], "aqiLv1": ["330", "50.3"], "aqiLv2": ["26", "3.96"], "aqiLv3": ["1", "0.15"], "aqiLv4": ["0", "0.0"], "aqiLv5": ["0", "0.0"]}, {"aqiLv0": ["414", "56.1"], "aqiLv1": ["310", "42.01"], "aqiLv2": ["14", "1.9"], "aqiLv3": ["0", "0.0"], "aqiLv4": ["0", "0.0"], "aqiLv5": ["0", "0.0"]}, {"aqiLv0": ["136", "21.55"], "aqiLv1": ["467", "74.01"], "aqiLv2": ["28", "4.44"], "aqiLv3": ["0", "0.0"], "aqiLv4": ["0", "0.0"], "aqiLv5": ["0", "0.0"]}, {"aqiLv0": ["310", "46.34"], "aqiLv1": ["355", "53.06"], "aqiLv2": ["4", "0.6"], "aqiLv3": ["0", "0.0"], "aqiLv4": ["0", "0.0"], "aqiLv5": ["0", "0.0"]}, {"aqiLv0": ["469", "75.28"], "aqiLv1": ["154", "24.72"], "aqiLv2": ["0", "0.0"], "aqiLv3": ["0", "0.0"], "aqiLv4": ["0", "0.0"], "aqiLv5": ["0", "0.0"]}, {"aqiLv0": ["477", "66.43"], "aqiLv1": ["238", "33.15"], "aqiLv2": ["3", "0.42"], "aqiLv3": ["0", "0.0"], "aqiLv4": ["0", "0.0"], "aqiLv5": ["0", "0.0"]}, {"aqiLv0": ["605", "81.54"], "aqiLv1": ["137", "18.46"], "aqiLv2": ["0", "0.0"], "aqiLv3": ["0", "0.0"], "aqiLv4": ["0", "0.0"], "aqiLv5": ["0", "0.0"]}, {"aqiLv0": ["609", "88.52"], "aqiLv1": ["79", "11.48"], "aqiLv2": ["0", "0.0"], "aqiLv3": ["0", "0.0"], "aqiLv4": ["0", "0.0"], "aqiLv5": ["0", "0.0"]}, {"aqiLv0": ["504", "70.89"], "aqiLv1": ["207", "29.11"], "aqiLv2": ["0", "0.0"], "aqiLv3": ["0", "0.0"], "aqiLv4": ["0", "0.0"], "aqiLv5": ["0", "0.0"]}, {"aqiLv0": ["578", "85.0"], "aqiLv1": ["102", "15.0"], "aqiLv2": ["0", "0.0"], "aqiLv3": ["0", "0.0"], "aqiLv4": ["0", "0.0"], "aqiLv5": ["0", "0.0"]}, {"aqiLv0": ["504", "71.9"], "aqiLv1": ["195", "27.82"], "aqiLv2": ["2", "0.29"], "aqiLv3": ["0", "0.0"], "aqiLv4": ["0", "0.0"], "aqiLv5": ["0", "0.0"]}], "SeasonAvgTmax": [24.0, 33.0, 26.0, 16.0], "SeasonAvgTmin": [15.0, 25.0, 20.0, 9.0], "SeasonAvgRain": [459.0, 659.0, 276.0, 189.0], "AqiFlag": "true"}}