{"101300602": {"yearAvgTemp": ["12", "14", "17", "22", "25", "27", "28", "28", "27", "23", "19", "13"], "yearAvgRainDay": ["10", "8", "14", "14", "18", "19", "16", "15", "11", "6", "10", "9"], "AqiFlag": "false", "yearAqi": [{"aqiLv1": ["-1", "-1"], "aqiLv0": ["-1", "-1"], "aqiLv3": ["-1", "-1"], "aqiLv2": ["-1", "-1"], "aqiLv5": ["-1", "-1"], "aqiLv4": ["-1", "-1"]}, {"aqiLv1": ["-1", "-1"], "aqiLv0": ["-1", "-1"], "aqiLv3": ["-1", "-1"], "aqiLv2": ["-1", "-1"], "aqiLv5": ["-1", "-1"], "aqiLv4": ["-1", "-1"]}, {"aqiLv1": ["-1", "-1"], "aqiLv0": ["-1", "-1"], "aqiLv3": ["-1", "-1"], "aqiLv2": ["-1", "-1"], "aqiLv5": ["-1", "-1"], "aqiLv4": ["-1", "-1"]}, {"aqiLv1": ["-1", "-1"], "aqiLv0": ["-1", "-1"], "aqiLv3": ["-1", "-1"], "aqiLv2": ["-1", "-1"], "aqiLv5": ["-1", "-1"], "aqiLv4": ["-1", "-1"]}, {"aqiLv1": ["-1", "-1"], "aqiLv0": ["-1", "-1"], "aqiLv3": ["-1", "-1"], "aqiLv2": ["-1", "-1"], "aqiLv5": ["-1", "-1"], "aqiLv4": ["-1", "-1"]}, {"aqiLv1": ["-1", "-1"], "aqiLv0": ["-1", "-1"], "aqiLv3": ["-1", "-1"], "aqiLv2": ["-1", "-1"], "aqiLv5": ["-1", "-1"], "aqiLv4": ["-1", "-1"]}, {"aqiLv1": ["-1", "-1"], "aqiLv0": ["-1", "-1"], "aqiLv3": ["-1", "-1"], "aqiLv2": ["-1", "-1"], "aqiLv5": ["-1", "-1"], "aqiLv4": ["-1", "-1"]}, {"aqiLv1": ["-1", "-1"], "aqiLv0": ["-1", "-1"], "aqiLv3": ["-1", "-1"], "aqiLv2": ["-1", "-1"], "aqiLv5": ["-1", "-1"], "aqiLv4": ["-1", "-1"]}, {"aqiLv1": ["-1", "-1"], "aqiLv0": ["-1", "-1"], "aqiLv3": ["-1", "-1"], "aqiLv2": ["-1", "-1"], "aqiLv5": ["-1", "-1"], "aqiLv4": ["-1", "-1"]}, {"aqiLv1": ["-1", "-1"], "aqiLv0": ["-1", "-1"], "aqiLv3": ["-1", "-1"], "aqiLv2": ["-1", "-1"], "aqiLv5": ["-1", "-1"], "aqiLv4": ["-1", "-1"]}, {"aqiLv1": ["-1", "-1"], "aqiLv0": ["-1", "-1"], "aqiLv3": ["-1", "-1"], "aqiLv2": ["-1", "-1"], "aqiLv5": ["-1", "-1"], "aqiLv4": ["-1", "-1"]}, {"aqiLv1": ["-1", "-1"], "aqiLv0": ["-1", "-1"], "aqiLv3": ["-1", "-1"], "aqiLv2": ["-1", "-1"], "aqiLv5": ["-1", "-1"], "aqiLv4": ["-1", "-1"]}], "yearMinTemp": ["9", "11", "14", "19", "22", "24", "25", "25", "24", "20", "15", "10"], "yearAvgRain": ["73", "27", "118", "154", "280", "226", "187", "178", "120", "58", "98", "56"], "yearMaxTemp": ["16", "19", "21", "26", "30", "32", "33", "33", "32", "28", "23", "18"], "SeasonAvgTmin": [18.0, 25.0, 20.0, 10.0], "SeasonAvgRain": [553.0, 591.0, 276.0, 157.0], "SeasonAvgTmax": [26.0, 33.0, 28.0, 17.0], "yearAvgHumidity": ["77", "76", "81", "80", "81", "82", "80", "80", "77", "73", "77", "73"], "yearAvgAqi": ["-1", "-1", "-1", "-1", "-1", "-1", "-1", "-1", "-1", "-1", "-1", "-1"]}}